{
  "id": "sistem-pengiriman-paket-env",
  "name": "Sistem Pengiriman Paket - Environment",
  "values": [
    {
      "key": "base_url",
      "value": "http://localhost",
      "enabled": true
    },
    {
      "key": "api_version",
      "value": "v1",
      "enabled": true
    },
    {
      "key": "auth_token",
      "value": "",
      "enabled": true
    },
    {
      "key": "customer_id",
      "value": "",
      "enabled": true
    },
    {
      "key": "package_id",
      "value": "1",
      "enabled": true
    },
    {
      "key": "hub_id",
      "value": "1",
      "enabled": true
    },
    {
      "key": "fleet_id",
      "value": "1",
      "enabled": true
    },
    {
      "key": "tracking_number",
      "value": "TRK00000001AB4A",
      "enabled": true
    },
    {
      "key": "warehouse_id",
      "value": "1",
      "enabled": true
    },
    {
      "key": "origin_hub_id",
      "value": "3",
      "enabled": true
    },
    {
      "key": "destination_hub_id",
      "value": "7",
      "enabled": true
    }
  ],
  "_postman_variable_scope": "environment",
  "_postman_exported_at": "2026-04-30T00:00:00.000Z",
  "_postman_exported_using": "Postman/v11.0.0"
}
